Boufti/__init__.py
Boufti/curation.py
Boufti/features.py
Boufti/image.py
Boufti/imagecollection.py
Boufti/measurements.py
Boufti/omni.py
Boufti/plot.py
Boufti/utilities.py
Boufti-0.0.1.dist-info/LICENSE
Boufti-0.0.1.dist-info/METADATA
Boufti-0.0.1.dist-info/WHEEL
Boufti-0.0.1.dist-info/top_level.txt
Boufti-0.0.1.dist-info/RECORD
