Metadata-Version: 2.1
Name: Boufti
Version: 0.0.1
Summary: A microscopy image analysis package
Author-email: Bart Steemans <bart.steemans@kuleuven.be>
Classifier: Programming Language :: Python :: 3
Classifier: License :: OSI Approved :: MIT License
Classifier: Operating System :: Microsoft :: Windows :: Windows 10
Requires-Python: >=3.10.8
License-File: LICENSE
